swannotebookviewer/__init__.py
swannotebookviewer/_version.py
swannotebookviewer/notebookviewer.py
swannotebookviewer-1.2.0.dist-info/METADATA
swannotebookviewer-1.2.0.dist-info/WHEEL
swannotebookviewer-1.2.0.dist-info/top_level.txt
swannotebookviewer-1.2.0.dist-info/RECORD
