Metadata-Version: 2.1
Name: swannotebookviewer
Version: 1.2.0
Summary: Extension that provides a Jupyter Notebook viewer as an endpoint
Home-page: https://github.com/swan-cern/jupyter-extensions
Author: SWAN Admins
License: AGPL-3.0
Keywords: Jupyter,Notebooks,SWAN,CERN
Platform: Linux
Platform: Mac OS X
Platform: Windows
Classifier: License :: OSI Approved :: GNU Affero General Public License v3
Classifier: Programming Language :: Python
Classifier: Programming Language :: Python :: 3
Classifier: Programming Language :: Python :: 3.5
Classifier: Programming Language :: Python :: 3.6
Classifier: Programming Language :: Python :: 3.7
Classifier: Programming Language :: Python :: 3.8
Classifier: Framework :: Jupyter
Requires-Dist: notebook
Requires-Dist: nbconvert (>=6.0)
